{
  "info": {
    "_postman_id": "doctor365-complete-api",
    "name": "Doctor365 Complete API",
    "description": "Complete API collection for Doctor365 microservices - Auth, Patients, Doctors, Appointments",
    "schema": "https://schema.getpostman.com/json/collection/v2.1.0/collection.json"
  },
  "item": [
    {
      "name": "AUTH SERVICE",
      "item": [
        {
          "name": "Register Patient",
          "request": {
            "method": "POST",
            "header": [
              {
                "key": "Content-Type",
                "value": "application/json"
              }
            ],
            "body": {
              "mode": "raw",
              "raw": "{\n  \"email\": \"patient@test.com\",\n  \"password\": \"password123\",\n  \"firstName\": \"John\",\n  \"lastName\": \"Doe\",\n  \"role\": \"patient\"\n}"
            },
            "url": {
              "raw": "http://localhost:5001/auth/register",
              "protocol": "http",
              "host": ["localhost"],
              "port": "5001",
              "path": ["auth", "register"]
            },
            "description": "Register a new patient user. Save the returned id as PATIENT_ID and accessToken as PATIENT_TOKEN"
          },
          "response": []
        },
        {
          "name": "Register Doctor",
          "request": {
            "method": "POST",
            "header": [
              {
                "key": "Content-Type",
                "value": "application/json"
              }
            ],
            "body": {
              "mode": "raw",
              "raw": "{\n  \"email\": \"doctor@test.com\",\n  \"password\": \"password123\",\n  \"firstName\": \"Dr. Jane\",\n  \"lastName\": \"Smith\",\n  \"role\": \"doctor\"\n}"
            },
            "url": {
              "raw": "http://localhost:5001/auth/register",
              "protocol": "http",
              "host": ["localhost"],
              "port": "5001",
              "path": ["auth", "register"]
            },
            "description": "Register a new doctor user. Save the returned id as DOCTOR_ID and accessToken as DOCTOR_TOKEN"
          },
          "response": []
        },
        {
          "name": "Login Patient",
          "request": {
            "method": "POST",
            "header": [
              {
                "key": "Content-Type",
                "value": "application/json"
              }
            ],
            "body": {
              "mode": "raw",
              "raw": "{\n  \"email\": \"patient@test.com\",\n  \"password\": \"password123\"\n}"
            },
            "url": {
              "raw": "http://localhost:5001/auth/login",
              "protocol": "http",
              "host": ["localhost"],
              "port": "5001",
              "path": ["auth", "login"]
            },
            "description": "Login as patient. Get fresh accessToken"
          },
          "response": []
        },
        {
          "name": "Refresh Token",
          "request": {
            "method": "POST",
            "header": [
              {
                "key": "Content-Type",
                "value": "application/json"
              }
            ],
            "body": {
              "mode": "raw",
              "raw": "{\n  \"refreshToken\": \"{{refresh_token}}\"\n}"
            },
            "url": {
              "raw": "http://localhost:5001/auth/refresh-token",
              "protocol": "http",
              "host": ["localhost"],
              "port": "5001",
              "path": ["auth", "refresh-token"]
            },
            "description": "Get new accessToken using refreshToken. Use this when token expires"
          },
          "response": []
        },
        {
          "name": "Logout",
          "request": {
            "method": "POST",
            "header": [
              {
                "key": "Authorization",
                "value": "Bearer {{patient_token}}"
              }
            ],
            "url": {
              "raw": "http://localhost:5001/auth/logout",
              "protocol": "http",
              "host": ["localhost"],
              "port": "5001",
              "path": ["auth", "logout"]
            },
            "description": "Logout (requires valid JWT token)"
          },
          "response": []
        }
      ]
    },
    {
      "name": "DOCTOR SERVICE",
      "item": [
        {
          "name": "Get All Doctors (Public)",
          "request": {
            "method": "GET",
            "header": [],
            "url": {
              "raw": "http://localhost:5003/api/doctors",
              "protocol": "http",
              "host": ["localhost"],
              "port": "5003",
              "path": ["api", "doctors"]
            },
            "description": "Get list of all doctors (public endpoint, no auth required)"
          },
          "response": []
        },
        {
          "name": "Get Doctor by ID (Public)",
          "request": {
            "method": "GET",
            "header": [],
            "url": {
              "raw": "http://localhost:5003/api/doctors/{{doctor_id}}",
              "protocol": "http",
              "host": ["localhost"],
              "port": "5003",
              "path": ["api", "doctors", "{{doctor_id}}"]
            },
            "description": "Get specific doctor details by ID (public endpoint)"
          },
          "response": []
        },
        {
          "name": "Get My Doctor Profile",
          "request": {
            "method": "GET",
            "header": [
              {
                "key": "Authorization",
                "value": "Bearer {{doctor_token}}"
              }
            ],
            "url": {
              "raw": "http://localhost:5003/api/doctors/me",
              "protocol": "http",
              "host": ["localhost"],
              "port": "5003",
              "path": ["api", "doctors", "me"]
            },
            "description": "Get your own doctor profile (requires doctor auth)"
          },
          "response": []
        },
        {
          "name": "Update My Doctor Profile",
          "request": {
            "method": "PUT",
            "header": [
              {
                "key": "Authorization",
                "value": "Bearer {{doctor_token}}"
              },
              {
                "key": "Content-Type",
                "value": "application/json"
              }
            ],
            "body": {
              "mode": "raw",
              "raw": "{\n  \"firstName\": \"Dr. Jane\",\n  \"lastName\": \"Smith\",\n  \"specialization\": \"Cardiology\",\n  \"licenseNumber\": \"LIC123456\",\n  \"yearsOfExperience\": 5,\n  \"consultationFee\": 50,\n  \"availability\": [\"Monday\", \"Tuesday\", \"Wednesday\"],\n  \"hospitalOrClinic\": \"City Hospital\"\n}"
            },
            "url": {
              "raw": "http://localhost:5003/api/doctors/me",
              "protocol": "http",
              "host": ["localhost"],
              "port": "5003",
              "path": ["api", "doctors", "me"]
            },
            "description": "Update your doctor profile"
          },
          "response": []
        }
      ]
    },
    {
      "name": "PATIENT SERVICE",
      "item": [
        {
          "name": "Get My Patient Profile",
          "request": {
            "method": "GET",
            "header": [
              {
                "key": "Authorization",
                "value": "Bearer {{patient_token}}"
              }
            ],
            "url": {
              "raw": "http://localhost:5002/api/patients/me",
              "protocol": "http",
              "host": ["localhost"],
              "port": "5002",
              "path": ["api", "patients", "me"]
            },
            "description": "Get your own patient profile"
          },
          "response": []
        },
        {
          "name": "Update My Patient Profile",
          "request": {
            "method": "PUT",
            "header": [
              {
                "key": "Authorization",
                "value": "Bearer {{patient_token}}"
              },
              {
                "key": "Content-Type",
                "value": "application/json"
              }
            ],
            "body": {
              "mode": "raw",
              "raw": "{\n  \"firstName\": \"John\",\n  \"lastName\": \"Doe\",\n  \"dateOfBirth\": \"1990-05-15\",\n  \"gender\": \"male\",\n  \"phone\": \"+94771234567\",\n  \"address\": \"123 Main St, Colombo\",\n  \"emergencyContact\": \"+94772234567\",\n  \"medicalHistorySummary\": \"No known allergies\"\n}"
            },
            "url": {
              "raw": "http://localhost:5002/api/patients/me",
              "protocol": "http",
              "host": ["localhost"],
              "port": "5002",
              "path": ["api", "patients", "me"]
            },
            "description": "Update your patient profile"
          },
          "response": []
        },
        {
          "name": "Get All Patients (Admin)",
          "request": {
            "method": "GET",
            "header": [
              {
                "key": "Authorization",
                "value": "Bearer {{admin_token}}"
              }
            ],
            "url": {
              "raw": "http://localhost:5002/api/patients",
              "protocol": "http",
              "host": ["localhost"],
              "port": "5002",
              "path": ["api", "patients"]
            },
            "description": "Get all patients (admin only)"
          },
          "response": []
        }
      ]
    },
    {
      "name": "APPOINTMENT SERVICE",
      "item": [
        {
          "name": "Health Check",
          "request": {
            "method": "GET",
            "header": [],
            "url": {
              "raw": "http://localhost:5004/health",
              "protocol": "http",
              "host": ["localhost"],
              "port": "5004",
              "path": ["health"]
            },
            "description": "Check if appointment service is running"
          },
          "response": []
        },
        {
          "name": "Create Appointment",
          "request": {
            "method": "POST",
            "header": [
              {
                "key": "Authorization",
                "value": "Bearer {{patient_token}}"
              },
              {
                "key": "Content-Type",
                "value": "application/json"
              }
            ],
            "body": {
              "mode": "raw",
              "raw": "{\n  \"doctorId\": \"{{doctor_id}}\",\n  \"appointmentDate\": \"2026-04-15T10:00:00Z\",\n  \"appointmentTime\": \"10:30\",\n  \"reason\": \"General checkup\",\n  \"notes\": \"First consultation\"\n}"
            },
            "url": {
              "raw": "http://localhost:5004/api/appointments",
              "protocol": "http",
              "host": ["localhost"],
              "port": "5004",
              "path": ["api", "appointments"]
            },
            "description": "Create new appointment (patient only). Replace {{doctor_id}} with actual doctor's user ID"
          },
          "response": []
        },
        {
          "name": "Get My Appointments",
          "request": {
            "method": "GET",
            "header": [
              {
                "key": "Authorization",
                "value": "Bearer {{patient_token}}"
              }
            ],
            "url": {
              "raw": "http://localhost:5004/api/appointments/me",
              "protocol": "http",
              "host": ["localhost"],
              "port": "5004",
              "path": ["api", "appointments", "me"]
            },
            "description": "Get your appointments (patient/doctor can see their own)"
          },
          "response": []
        },
        {
          "name": "Get Doctor's Appointments",
          "request": {
            "method": "GET",
            "header": [
              {
                "key": "Authorization",
                "value": "Bearer {{doctor_token}}"
              }
            ],
            "url": {
              "raw": "http://localhost:5004/api/appointments/me",
              "protocol": "http",
              "host": ["localhost"],
              "port": "5004",
              "path": ["api", "appointments", "me"]
            },
            "description": "Get appointments assigned to you (doctor view)"
          },
          "response": []
        },
        {
          "name": "Get Appointment by ID",
          "request": {
            "method": "GET",
            "header": [
              {
                "key": "Authorization",
                "value": "Bearer {{patient_token}}"
              }
            ],
            "url": {
              "raw": "http://localhost:5004/api/appointments/{{appointment_id}}",
              "protocol": "http",
              "host": ["localhost"],
              "port": "5004",
              "path": ["api", "appointments", "{{appointment_id}}"]
            },
            "description": "Get specific appointment details"
          },
          "response": []
        },
        {
          "name": "Update Appointment Status (Doctor)",
          "request": {
            "method": "PATCH",
            "header": [
              {
                "key": "Authorization",
                "value": "Bearer {{doctor_token}}"
              },
              {
                "key": "Content-Type",
                "value": "application/json"
              }
            ],
            "body": {
              "mode": "raw",
              "raw": "{\n  \"status\": \"confirmed\"\n}"
            },
            "url": {
              "raw": "http://localhost:5004/api/appointments/{{appointment_id}}/status",
              "protocol": "http",
              "host": ["localhost"],
              "port": "5004",
              "path": ["api", "appointments", "{{appointment_id}}", "status"]
            },
            "description": "Doctor confirms appointment. Status can be: pending, confirmed, cancelled, completed"
          },
          "response": []
        },
        {
          "name": "Update Appointment (Patient)",
          "request": {
            "method": "PUT",
            "header": [
              {
                "key": "Authorization",
                "value": "Bearer {{patient_token}}"
              },
              {
                "key": "Content-Type",
                "value": "application/json"
              }
            ],
            "body": {
              "mode": "raw",
              "raw": "{\n  \"appointmentDate\": \"2026-04-16T10:00:00Z\",\n  \"appointmentTime\": \"11:00\",\n  \"reason\": \"Need urgent consultation\",\n  \"notes\": \"Updated notes\"\n}"
            },
            "url": {
              "raw": "http://localhost:5004/api/appointments/{{appointment_id}}",
              "protocol": "http",
              "host": ["localhost"],
              "port": "5004",
              "path": ["api", "appointments", "{{appointment_id}}"]
            },
            "description": "Update appointment details (patient can only update pending appointments)"
          },
          "response": []
        },
        {
          "name": "Delete Appointment (Patient)",
          "request": {
            "method": "DELETE",
            "header": [
              {
                "key": "Authorization",
                "value": "Bearer {{patient_token}}"
              }
            ],
            "url": {
              "raw": "http://localhost:5004/api/appointments/{{appointment_id}}",
              "protocol": "http",
              "host": ["localhost"],
              "port": "5004",
              "path": ["api", "appointments", "{{appointment_id}}"]
            },
            "description": "Delete pending appointment (patient only)"
          },
          "response": []
        }
      ]
    },
    {
      "name": "GATEWAY (Optional - All Services via Single Port)",
      "item": [
        {
          "name": "Gateway Health",
          "request": {
            "method": "GET",
            "header": [],
            "url": {
              "raw": "http://localhost:5000/health",
              "protocol": "http",
              "host": ["localhost"],
              "port": "5000",
              "path": ["health"]
            },
            "description": "Check if gateway is running"
          },
          "response": []
        },
        {
          "name": "Create Appointment via Gateway",
          "request": {
            "method": "POST",
            "header": [
              {
                "key": "Authorization",
                "value": "Bearer {{patient_token}}"
              },
              {
                "key": "Content-Type",
                "value": "application/json"
              }
            ],
            "body": {
              "mode": "raw",
              "raw": "{\n  \"doctorId\": \"{{doctor_id}}\",\n  \"appointmentDate\": \"2026-04-15T10:00:00Z\",\n  \"appointmentTime\": \"10:30\",\n  \"reason\": \"General checkup\",\n  \"notes\": \"First consultation\"\n}"
            },
            "url": {
              "raw": "http://localhost:5000/api/appointments",
              "protocol": "http",
              "host": ["localhost"],
              "port": "5000",
              "path": ["api", "appointments"]
            },
            "description": "Create appointment through gateway (port 5000 instead of 5004)"
          },
          "response": []
        },
        {
          "name": "Get My Appointments via Gateway",
          "request": {
            "method": "GET",
            "header": [
              {
                "key": "Authorization",
                "value": "Bearer {{patient_token}}"
              }
            ],
            "url": {
              "raw": "http://localhost:5000/api/appointments/me",
              "protocol": "http",
              "host": ["localhost"],
              "port": "5000",
              "path": ["api", "appointments", "me"]
            },
            "description": "Get appointments through gateway"
          },
          "response": []
        }
      ]
    },
    {
      "name": "ERROR TESTS (Negative Tests)",
      "item": [
        {
          "name": "Create Appointment - Missing Token (401)",
          "request": {
            "method": "POST",
            "header": [
              {
                "key": "Content-Type",
                "value": "application/json"
              }
            ],
            "body": {
              "mode": "raw",
              "raw": "{\n  \"doctorId\": \"{{doctor_id}}\",\n  \"appointmentDate\": \"2026-04-15T10:00:00Z\",\n  \"appointmentTime\": \"10:30\",\n  \"reason\": \"General checkup\"\n}"
            },
            "url": {
              "raw": "http://localhost:5004/api/appointments",
              "protocol": "http",
              "host": ["localhost"],
              "port": "5004",
              "path": ["api", "appointments"]
            },
            "description": "Test error: Missing authorization token (should return 401 NO_TOKEN)"
          },
          "response": []
        },
        {
          "name": "Patient Update Status (403 Forbidden)",
          "request": {
            "method": "PATCH",
            "header": [
              {
                "key": "Authorization",
                "value": "Bearer {{patient_token}}"
              },
              {
                "key": "Content-Type",
                "value": "application/json"
              }
            ],
            "body": {
              "mode": "raw",
              "raw": "{\n  \"status\": \"confirmed\"\n}"
            },
            "url": {
              "raw": "http://localhost:5004/api/appointments/{{appointment_id}}/status",
              "protocol": "http",
              "host": ["localhost"],
              "port": "5004",
              "path": ["api", "appointments", "{{appointment_id}}", "status"]
            },
            "description": "Test error: Patient trying to update status (should return 403 FORBIDDEN)"
          },
          "response": []
        },
        {
          "name": "Invalid Appointment Date (400)",
          "request": {
            "method": "POST",
            "header": [
              {
                "key": "Authorization",
                "value": "Bearer {{patient_token}}"
              },
              {
                "key": "Content-Type",
                "value": "application/json"
              }
            ],
            "body": {
              "mode": "raw",
              "raw": "{\n  \"doctorId\": \"{{doctor_id}}\",\n  \"appointmentDate\": \"2020-04-15T10:00:00Z\",\n  \"appointmentTime\": \"10:30\",\n  \"reason\": \"General checkup\"\n}"
            },
            "url": {
              "raw": "http://localhost:5004/api/appointments",
              "protocol": "http",
              "host": ["localhost"],
              "port": "5004",
              "path": ["api", "appointments"]
            },
            "description": "Test error: Past appointment date (should return 400 VALIDATION_ERROR)"
          },
          "response": []
        },
        {
          "name": "Invalid Time Format (400)",
          "request": {
            "method": "POST",
            "header": [
              {
                "key": "Authorization",
                "value": "Bearer {{patient_token}}"
              },
              {
                "key": "Content-Type",
                "value": "application/json"
              }
            ],
            "body": {
              "mode": "raw",
              "raw": "{\n  \"doctorId\": \"{{doctor_id}}\",\n  \"appointmentDate\": \"2026-04-15T10:00:00Z\",\n  \"appointmentTime\": \"25:70\",\n  \"reason\": \"General checkup\"\n}"
            },
            "url": {
              "raw": "http://localhost:5004/api/appointments",
              "protocol": "http",
              "host": ["localhost"],
              "port": "5004",
              "path": ["api", "appointments"]
            },
            "description": "Test error: Invalid time format (should return 400 VALIDATION_ERROR)"
          },
          "response": []
        }
      ]
    }
  ],
  "variable": [
    {
      "key": "patient_token",
      "value": "",
      "type": "string"
    },
    {
      "key": "doctor_token",
      "value": "",
      "type": "string"
    },
    {
      "key": "admin_token",
      "value": "",
      "type": "string"
    },
    {
      "key": "patient_id",
      "value": "",
      "type": "string"
    },
    {
      "key": "doctor_id",
      "value": "",
      "type": "string"
    },
    {
      "key": "appointment_id",
      "value": "",
      "type": "string"
    },
    {
      "key": "refresh_token",
      "value": "",
      "type": "string"
    }
  ]
}
